[{"id":"01963de7-00ef-70ea-90f1-cc1cc00f0757","parentId":null,"rootId":null,"fromId":875,"content":"10年前实习2000块钱，现在实习3000不少了，专科毕业入职就4500块大概","createdAt":"2023-08-27T13:32:24"},{"id":"01963de7-0135-7245-8f9c-2e4ea974b35c","parentId":null,"rootId":null,"fromId":5431,"content":"我也是实习，一天一百，硕士研究生（黑脸）","createdAt":"2023-08-27T15:48:31"},{"id":"01963de7-017a-70ad-8ff3-727dd1a4097a","parentId":null,"rootId":null,"fromId":5497,"content":"啊，也是济南吗？","createdAt":"2023-08-27T18:13:36"},{"id":"01963de7-0195-70fc-9804-e49453500f11","parentId":null,"rootId":null,"fromId":1398,"content":"毕业了就不能叫实习了\n","createdAt":"2023-08-27T20:29:46"},{"id":"01963de7-017f-70c1-bc9f-11779c6cab4f","parentId":null,"rootId":null,"fromId":5431,"content":"是的，而且不是大公司，导师给找的小地方","createdAt":"2023-08-28T07:08:46"},{"id":"01963de7-0183-7284-8312-43de86214fe8","parentId":null,"rootId":null,"fromId":258,"content":"明显坑你","createdAt":"2023-08-28T09:40:58"},{"id":"01963de7-0187-70aa-abdd-e46b3e64ce5b","parentId":null,"rootId":null,"fromId":3705,"content":"快run","createdAt":"2023-08-28T15:48:27"},{"id":"01963de7-018c-7283-a386-97f737b0e18d","parentId":null,"rootId":null,"fromId":3705,"content":"有点少，看看转正多少吧","createdAt":"2023-08-28T15:49:00"},{"id":"01963de7-01da-721b-bd1d-b9da3f30eed4","parentId":null,"rootId":null,"fromId":3277,"content":"还行，涨了500","createdAt":"2023-08-28T22:43:12"},{"id":"01963de7-021d-70e4-b1ea-bb6886464d01","parentId":null,"rootId":null,"fromId":333,"content":"什么岗位啊","createdAt":"2023-08-29T09:02:27"},{"id":"01963de7-0261-7353-92bc-31ca2d30dad2","parentId":null,"rootId":null,"fromId":4253,"content":"毕业了就不能叫实习了，什么行业呢，工资偏低","createdAt":"2023-08-29T14:25:05"},{"id":"01963de7-02aa-7102-a628-e7dacb301a8c","parentId":null,"rootId":null,"fromId":3219,"content":"我实习的时候也是3000","createdAt":"2023-08-29T14:35:26"},{"id":"01963de7-0190-73c8-baf3-9d3daf32d658","parentId":null,"rootId":null,"fromId":5431,"content":"实习一个学期回学校，也算是导师帮忙干活也算是实习","createdAt":"2023-08-30T16:56:02"},{"id":"01963de7-02a5-7391-871e-9a300f5b5da2","parentId":null,"rootId":null,"fromId":5497,"content":"计算机","createdAt":"2023-09-09T09:25:07"}]