[{"id":"01963def-75fc-7201-84c5-e27b0f05562c","parentId":null,"rootId":null,"fromId":922,"content":"帮杰哥蹲一下","createdAt":"2024-05-22T09:41:58"},{"id":"01963def-7642-736d-bb3e-84ad752e41d3","parentId":null,"rootId":null,"fromId":1150,"content":"博乐通的不要不识好歹，快点出来给杰哥回一下","createdAt":"2024-05-22T09:47:09"},{"id":"01963def-7687-71d2-8fe2-fcf4bc99c85c","parentId":null,"rootId":null,"fromId":7475,"content":"6","createdAt":"2024-05-22T09:50:09"},{"id":"01963def-768c-7137-89fa-2bac643cba00","parentId":null,"rootId":null,"fromId":4087,"content":"又需要人去填坑了吗","createdAt":"2024-05-22T11:02:48"},{"id":"01963def-7690-708c-b26e-c5565d495e4d","parentId":null,"rootId":null,"fromId":576,"content":"相关案号：\n济高新劳仲案字(2023)第2060号\n(2024)鲁0191执762号\n当前审理程序日期：2024-02-22\n法院：\n济南高新技术产业开发区人民法院\n执行标的：108654.00元\n\n\n会玩。","createdAt":"2024-05-22T11:17:11"},{"id":"01963def-76d7-7110-8663-0b215928f36b","parentId":null,"rootId":null,"fromId":4087,"content":"我去 真有啊","createdAt":"2024-05-22T11:27:54"},{"id":"01963def-76ea-724d-b023-09153bb0d5b1","parentId":null,"rootId":null,"fromId":1889,"content":"投资人会投一个濒临破产的小公司么，兄弟。","createdAt":"2024-05-24T08:37:23"},{"id":"01963def-7730-7292-b91c-066e262fa1e8","parentId":null,"rootId":null,"fromId":933,"content":"不要打破杰哥的梦","createdAt":"2024-05-24T08:47:13"},{"id":"01963def-7734-7351-95b5-1f0ac0ed2ed9","parentId":null,"rootId":null,"fromId":1049,"content":"杰哥在博乐通吗？","createdAt":"2024-05-24T09:01:25"},{"id":"01963def-76db-71b2-9f1d-71aaa41b706e","parentId":null,"rootId":null,"fromId":735,"content":"这么多","createdAt":"2024-05-24T11:55:54"},{"id":"01963def-7739-7232-8d5c-4d6a7b2087a1","parentId":null,"rootId":null,"fromId":933,"content":"杰哥已经准备入职伯乐通了","createdAt":"2024-05-26T09:57:24"},{"id":"01963def-773d-7267-b529-bf701bf65324","parentId":null,"rootId":null,"fromId":576,"content":"有个问题：濒临破产的公司该如何挽救呢？扶贫还是拯救？","createdAt":"2024-05-27T16:48:23"},{"id":"01963def-7742-7217-bf3d-d65fa5a55d95","parentId":null,"rootId":null,"fromId":4151,"content":"这么说吧兄弟，我在的时候，半年换了4个研发总监。","createdAt":"2024-06-05T18:11:03"},{"id":"01963def-785f-70bb-86d2-a70bcbc72a6f","parentId":null,"rootId":null,"fromId":7684,"content":"我是杰哥，兄弟们给我上！","createdAt":"2024-06-05T19:08:01"},{"id":"01963def-785b-72d2-b39e-cefdb6442432","parentId":null,"rootId":null,"fromId":7427,"content":"4个  牛批啊   6个月/4人 = 1.5个月一个","createdAt":"2024-06-12T18:01:54"},{"id":"01963def-78a3-7005-a332-03c85734ca0e","parentId":null,"rootId":null,"fromId":576,"content":"“牛批的公司”，7天体验卡，环游地球一周。","createdAt":"2024-06-20T12:11:58"},{"id":"01963def-78e7-700a-9729-83af17ce1a44","parentId":null,"rootId":null,"fromId":21429,"content":"驾校有推荐吗","createdAt":"2024-07-21T16:51:49"},{"id":"01963def-792d-71f5-bc54-9065175e94e6","parentId":null,"rootId":null,"fromId":198,"content":"老板长的跟个癞蛤蟆一样，说话呱呱呱的，人前人五人六的，人后都不能算是个人，认为员工喝西北风就能活，公司文化以爆粗口为荣，不论场合，不论身份，老板觉得自己能爆粗口自己就是牛逼， 谁来谁倒霉，公司人事流水线，这周来的人事，下周你可能就联系不上她了，干完之后老板认为欠债天经地义的事情，追债难如登天，深读宪法的朋友可以来试试整点赔偿金","createdAt":"2024-09-10T21:50:45"},{"id":"01963def-76e1-715a-ac86-b78ba3502fe7","parentId":null,"rootId":null,"fromId":21821,"content":"从哪里可以搜到内容呀","createdAt":"2024-12-19T23:06:01"},{"id":"01963def-76e6-738e-9203-75f3cb2eabcd","parentId":null,"rootId":null,"fromId":21821,"content":"从哪里能查这个案件的详细内容呀","createdAt":"2025-01-23T15:41:29"}]