[{"id":"01963de8-b30e-73c2-bf3f-57397b5c094a","parentId":null,"rootId":null,"fromId":1049,"content":"刚毕业到手8000可以了，再换一个不一定比这个高","createdAt":"2023-10-06T10:31:14"},{"id":"01963de8-b351-70d4-b3a7-5033ceb0249f","parentId":null,"rootId":null,"fromId":5546,"content":"对，现在也有这样的顾虑，就是工作比较痛苦，本人社恐，做销售性质的工作，和人打交道比较折磨","createdAt":"2023-10-06T13:12:20"},{"id":"01963de8-b355-71a1-afa5-934d5ff453c0","parentId":null,"rootId":null,"fromId":1398,"content":"你这个工资很高了","createdAt":"2023-10-06T16:28:31"},{"id":"01963de8-b39a-704b-9993-32baf9605ebd","parentId":null,"rootId":null,"fromId":1398,"content":"可以边投边工作(°∀°)ﾉ","createdAt":"2023-10-06T18:45:30"},{"id":"01963de8-b3e2-70e6-952a-57016c92ea75","parentId":null,"rootId":null,"fromId":508,"content":"不降低工资标准的话，难换。如果继续在同一行业发展，建议第一份工作至少干到明年7月。","createdAt":"2023-10-07T13:45:22"},{"id":"01963de8-b426-7339-9468-b28674296ad1","parentId":null,"rootId":null,"fromId":5546,"content":"未来行业还没想好，感觉不太好转行了，想下个工作转岗，专职售前，不想做销售","createdAt":"2023-10-07T15:55:48"}]