[{"id":"01963df5-2e36-72c5-996c-aa4ec55c4384","parentId":null,"rootId":null,"fromId":21912,"content":"公司做软件的，体系成熟，准备调整架构，把几个高薪高文凭的优化掉，换成刚毕业的大学生。一个差不多能换5个劳动力","createdAt":"2024-12-04T10:45:48"},{"id":"01963df5-2e82-7155-8091-3c112268f38e","parentId":null,"rootId":null,"fromId":5471,"content":"直接找初中分流的培训俩月开始干，岂不是更省钱","createdAt":"2024-12-04T11:04:17"},{"id":"01963df5-2e87-7116-abc4-aeb61d56c095","parentId":null,"rootId":null,"fromId":21912,"content":"有道理，毕竟能力强都搭好框架，流水线了，也用不着他们了。初中还不太行，起码大专吧，做软件还是得有点门槛和能力的，山东的学生确实不错","createdAt":"2024-12-04T11:20:53"},{"id":"01963df5-2e8b-707d-b90a-1f0a81860faa","parentId":null,"rootId":null,"fromId":875,"content":"体系成熟，架构清晰，能力再强，你不被裁谁被裁？","createdAt":"2024-12-04T12:39:13"},{"id":"01963df5-2ed9-7381-b813-851cb8f6edd3","parentId":null,"rootId":null,"fromId":4367,"content":"我985硕，高学历不等于高能力我也是认可的。我刚毕业在北京的一家公司，职位和我硕士研究方面十分重合，但是我是懵逼的度过了三个月，那会带我的本科大哥可能也觉得我是个憨逼吧。现在工作了三年半了，跳了几家公司，自己也带着个小团队。从别人夸我的话来总结，硕士带给我的就是知识整合、搜集能力，学习能力，跟踪前沿速度（这个用的越来越少了），还有一个PPT、文档能力。现在想想研究生做的一坨，有点难以回首，但是和本科毕业直接工作的人相比，切入同一个领域的角度不同，结果就是思维方式很不相同。","createdAt":"2024-12-04T14:35:00"},{"id":"01963df5-2ede-73f4-8b1d-6ead6de00cad","parentId":null,"rootId":null,"fromId":2428,"content":"你公司里本科毕业5年就能当架构师了吗，都这么吊？架构师是什么水平的架构师","createdAt":"2024-12-05T09:34:17"}]