[{"id":"01963de7-d09a-73b3-bebc-3f21f654285b","parentId":null,"rootId":null,"fromId":336,"content":"这得看你面试啥岗位，普通搬砖的一般不背调，即使被调也就问问入职时间和离职时间","createdAt":"2023-09-08T14:12:02"},{"id":"01963de7-d0f7-713d-af89-f785c648cbbe","parentId":null,"rootId":null,"fromId":3892,"content":"大公司也不背调吗？就是普联、山大地纬这种规模的","createdAt":"2023-09-08T14:12:51"},{"id":"01963de7-d0fc-7174-829f-4fc87037faff","parentId":null,"rootId":null,"fromId":3892,"content":"我的想法就是工作年限不够，想在简历上延长一下","createdAt":"2023-09-08T14:13:32"},{"id":"01963de7-d100-72bc-91fc-a2b8321c571b","parentId":null,"rootId":null,"fromId":336,"content":"普联不背调 山大地纬不清楚了","createdAt":"2023-09-08T14:16:59"},{"id":"01963de7-d104-7026-96a4-e6248a90237e","parentId":null,"rootId":null,"fromId":3892,"content":"请问老哥，你是普联的吗？\n","createdAt":"2023-09-08T14:17:36"},{"id":"01963de7-d10a-726d-9d00-3e545a0dee72","parentId":null,"rootId":null,"fromId":336,"content":"不是 有朋友在那","createdAt":"2023-09-08T14:19:09"},{"id":"01963de7-d10e-72ec-8a2b-fc3beea92f64","parentId":null,"rootId":null,"fromId":4171,"content":"你是想跳槽还是刚培训完培训机构教你简历造假。前者的话无所谓，正常跳槽没必要包装，工作经历实话实说就行一般不会狠抓这个点，除非你是频繁跳槽。。后者的话就赌运气了，想查的话再包装也没用，查查社保就知道了。","createdAt":"2023-09-08T14:19:34"},{"id":"01963de7-d112-707a-9379-d207633b9c2d","parentId":null,"rootId":null,"fromId":336,"content":"只要能力和经验大差不差 适当的美化一下 一般都没啥问题","createdAt":"2023-09-08T14:22:10"},{"id":"01963de7-d117-7180-9afd-54a00068b3f5","parentId":null,"rootId":null,"fromId":3892,"content":"感谢诸位的建议","createdAt":"2023-09-08T14:27:44"},{"id":"01963de7-d15c-72c1-8301-d61e13c1931f","parentId":null,"rootId":null,"fromId":875,"content":"小公司能招到人就不错了，还挑肥捡瘦","createdAt":"2023-09-08T14:36:34"},{"id":"01963de7-d1a0-72ec-916d-806679db1fe8","parentId":null,"rootId":null,"fromId":3892,"content":"这不是想去个大公司吗？担心大公司背调严格。哈哈哈","createdAt":"2023-09-08T14:38:10"},{"id":"01963de7-d1a5-719f-b24b-679bb52929d9","parentId":null,"rootId":null,"fromId":3585,"content":"包装一问便知，昨天我这边刚招了个实在人，实在话面试技术占60% 其余看眼缘","createdAt":"2023-09-08T14:47:23"},{"id":"01963de7-d1f7-708f-979c-12ec9eb0c3bb","parentId":null,"rootId":null,"fromId":3585,"content":"可以技术上适度优化一下过筛，包装经历什么的不妥当","createdAt":"2023-09-08T14:48:00"},{"id":"01963de7-d1fc-715f-8ed0-377b058a4c7e","parentId":null,"rootId":null,"fromId":3892,"content":"请问多大规模公司？背调了吗？\n","createdAt":"2023-09-08T14:49:36"},{"id":"01963de7-d200-71f4-9b49-ff2a9d03d0fa","parentId":null,"rootId":null,"fromId":875,"content":"小公司根本不用包装，周六上班，福利差，能招到人算他们烧高香","createdAt":"2023-09-10T20:59:17"}]