[{"id":"01963df7-49f9-721f-9fbb-d1c42662c163","parentId":null,"rootId":null,"fromId":1398,"content":"招后端吗？","createdAt":"2025-02-25T11:25:45"},{"id":"01963df7-4a3d-70df-b981-8950a9cde909","parentId":null,"rootId":null,"fromId":6018,"content":"怎么联系","createdAt":"2025-02-25T11:46:45"},{"id":"01963df7-4a81-701b-9dbd-71e2f63026ba","parentId":null,"rootId":null,"fromId":3279,"content":"公司名称？工作地点？单双休？五险一金缴纳比例？招聘只说职责和要求是不是有点，傲慢。","createdAt":"2025-02-25T11:47:43"},{"id":"01963df7-4acc-70bf-a7c8-8e128751b3d7","parentId":null,"rootId":null,"fromId":6018,"content":"Wx fuzhongqianxingyue","createdAt":"2025-02-25T11:50:00"},{"id":"01963df7-4ac4-7120-923b-44dff00a2204","parentId":null,"rootId":null,"fromId":22712,"content":"能给你说薪资空间就不错了","createdAt":"2025-02-25T11:50:04"},{"id":"01963df7-4ac9-7192-90f1-117e4cbde5e5","parentId":null,"rootId":null,"fromId":3279,"content":"虽然只是个闲聊天的地方，但是这样介绍增加了无形很多沟通成本。以小见大吧。","createdAt":"2025-02-25T11:53:32"},{"id":"01963df7-4b12-71f9-bd63-433c4f57558e","parentId":null,"rootId":null,"fromId":2598,"content":"怎么联系？","createdAt":"2025-02-25T12:56:06"},{"id":"01963df7-4b5a-7170-9313-04a3e7b03f26","parentId":null,"rootId":null,"fromId":2598,"content":"linC9512","createdAt":"2025-02-25T12:58:00"},{"id":"01963df7-4b9f-71da-9714-1b67c4c4f77a","parentId":null,"rootId":null,"fromId":1517,"content":"日了，傻逼公司跟我说现在我们只招985,211的了，双非的不考虑，傻逼公司，抱歉了各位老铁，不给他们帮忙了","createdAt":"2025-02-25T16:06:56"},{"id":"01963df7-4be5-737f-b6bf-02a6d7b0286e","parentId":null,"rootId":null,"fromId":22024,"content":"双一流呢？","createdAt":"2025-02-25T17:33:16"},{"id":"01963df7-4be9-72dd-a9b8-aa1f11b7d5a0","parentId":null,"rootId":null,"fromId":21396,"content":"haha,还是现在人太多了，公司都挑不过来了","createdAt":"2025-02-26T08:41:21"},{"id":"01963df7-4bee-7225-b85d-e9e7edd86bd4","parentId":null,"rootId":null,"fromId":4367,"content":"这钱招92的，不如直接说只招转行过来的 哈哈","createdAt":"2025-02-26T09:03:44"},{"id":"01963df7-4bf2-7156-8316-22461e3e08fd","parentId":null,"rootId":null,"fromId":5725,"content":"什么傻逼公司啊，我哭了(┬＿┬)","createdAt":"2025-02-26T09:37:25"},{"id":"01963df7-4bf6-7012-86f7-b2612502957d","parentId":null,"rootId":null,"fromId":21813,"content":"我这也找前端，不需要92，本科就行。急着找工作的伙伴们可以先试试，留个微信号啥的","createdAt":"2025-02-26T09:41:02"},{"id":"01963df7-4c3c-7234-90a5-dbdeef57fc44","parentId":null,"rootId":null,"fromId":764,"content":"要求多久到岗？","createdAt":"2025-02-26T10:03:02"},{"id":"01963df7-4c3f-7064-a106-9b0ca63da9de","parentId":null,"rootId":null,"fromId":5441,"content":"xhljgx","createdAt":"2025-02-26T10:32:45"},{"id":"01963df7-4c43-735a-b83d-529ce4d5e859","parentId":null,"rootId":null,"fromId":6018,"content":"fuzhongqianxingyue","createdAt":"2025-02-26T11:22:03"},{"id":"01963df7-4c47-732f-8bdc-16be82ee1ae4","parentId":null,"rootId":null,"fromId":5826,"content":"zh971130z","createdAt":"2025-02-26T13:08:05"},{"id":"01963df7-4c50-7028-a812-fc4ac94a2189","parentId":null,"rootId":null,"fromId":21813,"content":"到岗时间越快越好","createdAt":"2025-02-26T14:10:44"},{"id":"01963df7-4c4c-7076-b0e0-4d4015d4c0cb","parentId":null,"rootId":null,"fromId":22649,"content":"vjxzlyx","createdAt":"2025-02-27T16:12:22"}]