[{"id":"01963deb-5206-712c-b041-282923576ed2","parentId":null,"rootId":null,"fromId":1049,"content":"你在这问恐怕没有人能回答你，只要能考上，还有花钱搞不定的事？","createdAt":"2024-02-19T10:53:57"},{"id":"01963deb-524b-71bb-a15d-4b8854f80812","parentId":null,"rootId":null,"fromId":6344,"content":"这种事最好不要让公司知道，在公司眼里你的做法对公司没有任何益处，还会因为你要走而放弃你","createdAt":"2024-02-19T11:04:43"},{"id":"01963deb-5291-70d5-85fd-30a2084e5139","parentId":null,"rootId":null,"fromId":6664,"content":"所以说想问一问到时候需不需要让公司提供","createdAt":"2024-02-19T11:07:00"},{"id":"01963deb-5295-7168-8b85-76ce0107e598","parentId":null,"rootId":null,"fromId":3180,"content":"需要提供，但是可以申请面试完再提供，先和用人单位沟通，面试通过随体检材料提供","createdAt":"2024-02-19T17:52:45"}]