[{"id":"01963ddc-1ffa-7333-8f1a-aeab9c65eadc","parentId":null,"rootId":null,"fromId":193,"content":"1","createdAt":"2022-09-01T15:21:54"},{"id":"01963ddc-2043-7017-a3af-6606b0f24113","parentId":null,"rootId":null,"fromId":193,"content":"试一下","createdAt":"2022-09-01T15:22:13"},{"id":"01963ddc-20a7-71c3-bd88-27178b4a008e","parentId":null,"rootId":null,"fromId":193,"content":"评论完显示楼主啊，这是bug嘛?","createdAt":"2022-09-01T15:22:40"},{"id":"01963ddc-20f2-734a-9956-96b09f10afc1","parentId":null,"rootId":null,"fromId":193,"content":"进行了匿名化处理，无需登入注册","createdAt":"2022-09-01T15:24:16"},{"id":"01963ddc-2139-72bf-8cd8-e6d61fd84ef6","parentId":null,"rootId":null,"fromId":1259,"content":"没搜到啊","createdAt":"2022-09-01T15:36:48"},{"id":"01963ddc-219c-72fc-ac0f-96654438e999","parentId":null,"rootId":null,"fromId":193,"content":"太优秀了哈哈哈","createdAt":"2022-09-01T15:38:56"},{"id":"01963ddc-21e2-722b-8da5-97a77b89bea5","parentId":null,"rootId":null,"fromId":1238,"content":"bug太多啦","createdAt":"2022-09-01T15:46:11"},{"id":"01963ddc-2228-7259-8986-b7d93fae05fd","parentId":null,"rootId":null,"fromId":193,"content":"啥bug","createdAt":"2022-09-01T15:48:42"},{"id":"01963ddc-2290-7201-899b-d4555ec7712d","parentId":null,"rootId":null,"fromId":193,"content":"2","createdAt":"2022-09-01T16:00:35"},{"id":"01963ddc-22d8-71c0-a75e-d8a3a8a4dac3","parentId":null,"rootId":null,"fromId":330,"content":"报错了","createdAt":"2022-09-01T16:01:12"},{"id":"01963ddc-231c-72e8-9dea-6b1de052fb9b","parentId":null,"rootId":null,"fromId":1238,"content":"搜索结果点进去再返回 列表就重复一遍\n切出去再回来 列表也重复。右边➕ 背景偏移了","createdAt":"2022-09-01T16:01:29"},{"id":"01963ddc-2360-70b4-a4ad-03080b90f53b","parentId":null,"rootId":null,"fromId":193,"content":"这是爬虫爬的？","createdAt":"2022-09-01T16:32:51"},{"id":"01963ddc-23a4-73fc-a1e5-faab7231148d","parentId":null,"rootId":null,"fromId":14,"content":"爬虫爬的数据？","createdAt":"2022-09-01T16:35:31"},{"id":"01963ddc-23ea-71d3-8bc8-965fc35b76c9","parentId":null,"rootId":null,"fromId":14,"content":"小程序不是站长写的哦，应该是大佬爬虫搞得，小程序评论都是楼主标识应该是token写死了的原因，其他帖子评论不会有这种情况。","createdAt":"2022-09-01T16:37:19"},{"id":"01963ddc-242f-70a9-97f7-d392978b4fdf","parentId":null,"rootId":null,"fromId":193,"content":"可以做成全国性质的了，安省分类","createdAt":"2022-09-02T06:30:17"},{"id":"01963ddc-2474-71d2-8a22-ce6d7f1039d2","parentId":null,"rootId":null,"fromId":193,"content":"可以的站长","createdAt":"2022-09-02T09:06:31"},{"id":"01963ddc-24b9-708a-89bf-60e610874b99","parentId":null,"rootId":null,"fromId":193,"content":"可以","createdAt":"2022-09-02T13:48:25"},{"id":"01963ddc-24ff-718e-9311-db379f6154f5","parentId":null,"rootId":null,"fromId":1571,"content":"1","createdAt":"2022-09-02T19:49:27"},{"id":"01963ddc-2549-71ea-b90e-5098caee4587","parentId":null,"rootId":null,"fromId":193,"content":"支持","createdAt":"2022-09-03T09:09:30"},{"id":"01963ddc-2598-72c5-baee-8d98a23c5ec2","parentId":null,"rootId":null,"fromId":193,"content":"样式在调整下","createdAt":"2022-09-03T21:52:45"},{"id":"01963ddc-25e9-73c9-b6fc-8e7bcc8f015d","parentId":null,"rootId":null,"fromId":933,"content":"666","createdAt":"2022-09-05T08:56:52"},{"id":"01963ddc-263f-73ca-a498-078cb1983655","parentId":null,"rootId":null,"fromId":59,"content":"太牛了 大佬","createdAt":"2022-09-08T09:11:35"}]