[{"id":"01963df6-7e08-7348-8d30-635c682dfc12","parentId":null,"rootId":null,"fromId":875,"content":"北京上班的都放假回来了，济南的还在上班卷","createdAt":"2025-01-20T11:38:46"},{"id":"01963df6-7e4c-739e-9727-94dfdebb59cb","parentId":null,"rootId":null,"fromId":5791,"content":"24放假","createdAt":"2025-01-20T17:12:26"},{"id":"01963df6-7e93-7030-b76e-20f325c7d350","parentId":null,"rootId":null,"fromId":22256,"content":"我们放20天","createdAt":"2025-01-20T17:51:19"},{"id":"01963df6-7ed7-70aa-85b9-d8bf828c0bc0","parentId":null,"rootId":null,"fromId":875,"content":"看热搜，第一批回家过年的猫狗已经在路上了","createdAt":"2025-01-21T08:04:17"}]