[{"id":"0196ec92-875b-7386-af32-8907645d38e1","parentId":null,"rootId":null,"fromId":7650,"content":"浪潮的项目经理岗位，工作饱和不，项目坑多不","createdAt":"2025-05-20T15:22:28"},{"id":"0196ecaf-dc22-73a6-8760-db68f0442b52","parentId":null,"rootId":null,"fromId":24326,"content":"别的项目我不知道，我在的事业部，项目经理一共3个人，每天晚上10点打底，目前项目经理的岗位也不是很多，但我们事业部还有一个外包岗位在招聘","createdAt":"2025-05-20T15:54:30"},{"id":"0196f0ee-12ec-7215-aeb9-0525193f2342","parentId":null,"rootId":null,"fromId":23027,"content":"来众阳吗？","createdAt":"2025-05-21T11:40:56"},{"id":"0196f10c-7ecb-727d-b3f0-3974c02582ce","parentId":null,"rootId":null,"fromId":24326,"content":"如果有机会内推，我可以去","createdAt":"2025-05-21T12:14:10"},{"id":"0196f29c-c469-731e-b902-d468ffd9d4e0","parentId":null,"rootId":null,"fromId":23027,"content":"你真饿了","createdAt":"2025-05-21T19:31:22"},{"id":"0197159d-3598-72ad-b494-abf58e0bcf3a","parentId":null,"rootId":null,"fromId":24560,"content":"你狠","createdAt":"2025-05-28T14:38:33"}]