[{"id":"01963df1-b318-73cf-bbe8-f962e8d0dda7","parentId":null,"rootId":null,"fromId":5725,"content":"哪两家公司啊，避雷","createdAt":"2024-07-09T14:11:52"},{"id":"01963df1-b35c-7189-a0c1-515c79be5ac3","parentId":null,"rootId":null,"fromId":7465,"content":"避雷避雷","createdAt":"2024-07-09T14:12:41"},{"id":"01963df1-b3a0-70cf-8f77-12d8beafa03b","parentId":null,"rootId":null,"fromId":3884,"content":"不好直接提名字,一提就猜出我是谁了,只能说是某区的城投公司和省属企业的某子公司","createdAt":"2024-07-09T14:16:24"},{"id":"01963df1-b3e8-705a-a1ee-fd6c3c086826","parentId":null,"rootId":null,"fromId":6039,"content":"又拿1个月补偿","createdAt":"2024-07-09T14:18:57"},{"id":"01963df1-b42e-71c1-8ae9-4cfa1f78fb2f","parentId":null,"rootId":null,"fromId":3884,"content":"劳务派遣,这回没补偿了","createdAt":"2024-07-09T14:19:17"},{"id":"01963df1-b3e4-735f-9796-119b35987a1c","parentId":null,"rootId":null,"fromId":6266,"content":"cxjsjt吗","createdAt":"2024-07-09T16:31:47"},{"id":"01963df1-b432-71e7-b1a3-69880137c077","parentId":null,"rootId":null,"fromId":2408,"content":"搞技术真的没意思，从入职当天就考虑被裁员怎么办，身心俱疲","createdAt":"2024-07-10T10:29:46"},{"id":"01963df1-b477-716c-9144-82a08f69d496","parentId":null,"rootId":null,"fromId":875,"content":"萝卜快跑啥时候来济南呀，迫不及待了","createdAt":"2024-07-10T20:04:12"},{"id":"01963df1-b4bb-7007-b84a-7c9bef951111","parentId":null,"rootId":null,"fromId":875,"content":"成立一个定制出租车公司，干运输吧，买上几辆萝卜","createdAt":"2024-07-13T11:48:14"}]