[{"id":"01963ddc-1468-7162-8a53-824a23819022","parentId":null,"rootId":null,"fromId":772,"content":"听说  市政府   省委   这些单位都不错","createdAt":"2022-08-31T10:52:19"},{"id":"01963ddc-14ac-7286-8439-4b1af1b8a210","parentId":null,"rootId":null,"fromId":965,"content":"好公司很多，只是上边有些公司太坑人了，其实有些小缺点可以忽略不计较，但这里面有些公司实在是太坑人了，去了就完蛋了","createdAt":"2022-08-31T11:25:41"},{"id":"01963ddc-14f2-7070-a545-e95c41a729c9","parentId":null,"rootId":null,"fromId":460,"content":"好的公司 谁给你内推啊 都是好朋友之间内推 资源共享嘛 不加班 公司领导nice的 薪资不抠的公司 其实济南一大把 但是都不可能离职 就算离职 也得想着好朋友之间内推","createdAt":"2022-08-31T11:31:41"},{"id":"01963ddc-1536-7257-9f61-f8df71fbc7ba","parentId":null,"rootId":null,"fromId":584,"content":"2楼老哥，好公司很多，给推荐几个","createdAt":"2022-08-31T13:50:21"},{"id":"01963ddc-157b-7314-9212-1eebca0306f4","parentId":null,"rootId":null,"fromId":815,"content":"道普信息计算有限公司。应该算吧","createdAt":"2022-08-31T14:00:34"},{"id":"01963ddc-15c7-72df-a01f-62ebc5d966ab","parentId":null,"rootId":null,"fromId":584,"content":"5楼 道普早都不招人了","createdAt":"2022-08-31T14:20:57"},{"id":"01963ddc-160e-71b6-b729-427a0a5afa94","parentId":null,"rootId":null,"fromId":1003,"content":"大哥 给推荐推荐吧","createdAt":"2022-08-31T14:21:26"},{"id":"01963ddc-165e-7130-bee8-dc9b28bb0424","parentId":null,"rootId":null,"fromId":712,"content":"还不错的公司，基本不离职，没坑位，而且就算招人，一般要求比较高，或者有时候看运气，正好缺人碰上了。","createdAt":"2022-08-31T15:15:05"},{"id":"01963ddc-16aa-70e2-a415-45bb951d23d4","parentId":null,"rootId":null,"fromId":336,"content":"我来推荐个：1：亚信很不错 2：众阳今年工资给的高的离谱 如果能接受他的缺点就今年的工资来说 相当牛批","createdAt":"2022-08-31T15:20:43"},{"id":"01963ddc-16f9-7236-88ec-678d55ec3ce2","parentId":null,"rootId":null,"fromId":1555,"content":"说众阳的好的是个拖吧，掏个税也没谁了","createdAt":"2022-08-31T16:31:22"},{"id":"01963ddc-1744-73ec-b46b-5cf314f148f3","parentId":null,"rootId":null,"fromId":336,"content":"不是拖不是拖 我就是看着我同事去了那直接工资翻番羡慕了！！！","createdAt":"2022-08-31T16:38:49"},{"id":"01963ddc-17cf-7312-87f5-af795d7c5c41","parentId":null,"rootId":null,"fromId":808,"content":"有一说一众阳靠这几年医疗健康，薪资还是可以的，但是背后就是出差，没有五险一金，还有加班严重。总的来说，有苦就有甜。","createdAt":"2022-08-31T16:52:56"},{"id":"01963ddc-1814-739c-8baf-1b1039e947a9","parentId":null,"rootId":null,"fromId":336,"content":"哦 我说怎么今年舍得给那么多钱，原来是赚麻了","createdAt":"2022-08-31T17:20:05"},{"id":"01963ddc-189c-729e-958a-229cc31df7db","parentId":null,"rootId":null,"fromId":336,"content":"具体给多少还真不知道！！一个同事一年经验给了13 还有一个四年左右给了15","createdAt":"2022-09-01T08:37:34"},{"id":"01963ddc-18e6-7301-9208-b39638b5df1c","parentId":null,"rootId":null,"fromId":768,"content":"众阳的缺点简直罄竹难书，尤其是老东西们给你洗脑他们当年的兄弟情，每个月开的那个舔狗会强迫全员谄媚，说众阳好的，可能是真没来众阳呆过","createdAt":"2022-09-01T13:58:12"},{"id":"01963ddc-192c-7085-8b63-6c14b873a0da","parentId":null,"rootId":null,"fromId":336,"content":"确实是没在那待过。以前的时候对众阳是没啥好印象的，就今年高薪招人才对他刮目相看了?","createdAt":"2022-09-01T14:06:12"},{"id":"01963ddc-19b5-7323-b045-b862cf28b8d9","parentId":null,"rootId":null,"fromId":193,"content":"111","createdAt":"2022-09-01T15:12:56"},{"id":"01963ddc-1a03-71ea-8053-77a2f9c846f8","parentId":null,"rootId":null,"fromId":193,"content":"22","createdAt":"2022-09-01T15:26:43"},{"id":"01963ddc-1a47-72f5-bd49-9282d6b9decf","parentId":null,"rootId":null,"fromId":193,"content":"我朋友从众阳下面的百灵走的，好个der","createdAt":"2022-09-01T16:27:43"},{"id":"01963ddc-1a8c-712e-b920-cd6f10e0e2ad","parentId":null,"rootId":null,"fromId":455,"content":"求几个好公司，大哥们有没，看黑名单看得我都害怕了","createdAt":"2022-09-02T08:58:55"},{"id":"01963ddc-1ace-7387-a36b-abdbe0266294","parentId":null,"rootId":null,"fromId":880,"content":"企业都还可以吧，主要是管理者太拉稀了，人心叵测的领导太多了，黑心老板太多了","createdAt":"2022-09-05T10:15:45"},{"id":"01963ddc-1b16-73c8-89f9-a55ae1c7d55a","parentId":null,"rootId":null,"fromId":860,"content":"亚信现在只招外包","createdAt":"2022-09-07T10:41:33"},{"id":"01963ddc-1b5b-7387-a787-250c6775de4f","parentId":null,"rootId":null,"fromId":1616,"content":"9楼说亚信的，千万别去济南西站那边那个点，那个北京移动CRM项目组的","createdAt":"2022-09-14T16:55:41"},{"id":"01963ddc-1ba1-733e-aa96-a2c61dcf9157","parentId":null,"rootId":null,"fromId":1616,"content":"不过话说说回来，济南西站那边的亚信应该也不会招人了，只招实习生","createdAt":"2022-09-14T16:57:47"},{"id":"01963ddc-15c1-708b-92d0-886f253966e0","parentId":null,"rootId":null,"fromId":3317,"content":"工资低也不涨工资呢~","createdAt":"2023-05-11T09:15:34"},{"id":"01963ddc-16f0-72cd-a579-f1d2a0113d6e","parentId":null,"rootId":null,"fromId":3636,"content":"笑死了，亚信？没去过好公司吗？","createdAt":"2023-09-18T16:05:26"},{"id":"01963ddc-16f5-720d-a473-96ae347b293e","parentId":null,"rootId":null,"fromId":6095,"content":"笑掉大牙了，亚信好？","createdAt":"2023-11-10T13:46:29"},{"id":"01963ddc-16a5-731c-ba50-d1db7fe8caaf","parentId":null,"rootId":null,"fromId":6170,"content":"给列举列举","createdAt":"2023-11-25T15:05:33"}]