[{"id":"01963de6-50c8-70e0-80d2-4d69ac013504","parentId":null,"rootId":null,"fromId":576,"content":"你能认可996  那全济南的公司都可以进的   就是工资会被腰斩","createdAt":"2023-08-14T18:22:27"},{"id":"01963de6-510d-70ca-a76b-efb84be1d8e5","parentId":null,"rootId":null,"fromId":875,"content":"不只是工资会少，社保公积金基数，年终奖，加班费，补充医疗保险，济南通通是最低或者没有，周六上班天经地义，不给钱","createdAt":"2023-08-14T18:28:14"},{"id":"01963de6-511e-73a4-82cb-3f3d8047e5e4","parentId":null,"rootId":null,"fromId":1398,"content":"我想去北京溜达溜达，楼主说一下什么公司","createdAt":"2023-08-14T20:10:44"},{"id":"01963de6-5162-728e-ac88-5b6d7b4833f4","parentId":null,"rootId":null,"fromId":3144,"content":"别回来了...找了两家.都TM的不发工资了....\n","createdAt":"2023-08-14T20:43:25"},{"id":"01963de6-5111-734c-8b0e-227729d1d29f","parentId":null,"rootId":null,"fromId":2935,"content":"首先，得发的下来工资，别的都好谈\n","createdAt":"2023-08-14T20:44:24"},{"id":"01963de6-51a6-7369-88ec-c961305cbeb9","parentId":null,"rootId":null,"fromId":1398,"content":"把公司报个名","createdAt":"2023-08-14T21:00:19"},{"id":"01963de6-51ab-7107-b845-52ef40bcdcfd","parentId":null,"rootId":null,"fromId":875,"content":"为了下一代的高考别这么卷，再累也得在北京干着，回济南干什么，为了继续卷高考？","createdAt":"2023-08-14T22:17:35"},{"id":"01963de6-51ee-72cb-8b25-1626c05d5528","parentId":null,"rootId":null,"fromId":3596,"content":"大佬，现在北京行情咋样？正打算去北京呢?","createdAt":"2023-08-14T23:09:20"},{"id":"01963de6-5234-705d-81aa-709a6a47c473","parentId":null,"rootId":null,"fromId":4087,"content":"济南很多公司都拖欠工资 报销","createdAt":"2023-08-15T00:22:40"},{"id":"01963de6-5278-7216-8cde-800369fbe8ea","parentId":null,"rootId":null,"fromId":2921,"content":"别来","createdAt":"2023-08-15T08:47:43"},{"id":"01963de6-5116-7081-a4dc-d41d93ec61a1","parentId":null,"rootId":null,"fromId":561,"content":"就这还有人说济南大环境并不差呢。怨自己不努力","createdAt":"2023-08-15T09:05:30"},{"id":"01963de6-52bd-72a0-ace9-8907d6407ab8","parentId":null,"rootId":null,"fromId":561,"content":"这种环境还有人在那说并不是济南大环境差，而是因为自己不够努力。这不是大环境什么才是大环境","createdAt":"2023-08-15T09:19:33"},{"id":"01963de6-530a-7317-8e0c-9ec85b6fd422","parentId":null,"rootId":null,"fromId":1751,"content":"济南996可是不给钱的奥","createdAt":"2023-08-15T11:11:00"},{"id":"01963de6-534f-7229-aa99-266ec99cb492","parentId":null,"rootId":null,"fromId":875,"content":"在济南歇不了，除非你能挤进国企央企，全额缴纳社保公积金，企业年金，补充医疗保险，双休，年假，饭补，应有尽有，不然去私企啥都没有","createdAt":"2023-08-15T11:30:41"},{"id":"01963de6-5306-73b6-8133-b0567ab15d18","parentId":null,"rootId":null,"fromId":2890,"content":"北京也一样，所以不想在这里了，想回去歇歇","createdAt":"2023-08-15T13:33:38"},{"id":"01963de6-5393-7181-ae27-dd04d5ecc239","parentId":null,"rootId":null,"fromId":2890,"content":"来过北京吗？来试试北京什么感觉？你以为来了北京什么都有了？要不是没办法了我能想着回去吗","createdAt":"2023-08-15T13:34:27"},{"id":"01963de6-5398-7247-894c-b2cc7fddc648","parentId":null,"rootId":null,"fromId":4142,"content":"北京大哥能详细说说么","createdAt":"2023-08-15T14:21:40"},{"id":"01963de6-539c-70a3-864c-07e303751280","parentId":null,"rootId":null,"fromId":875,"content":"在北京都吃不开，回来更不行，北京大部分都是双休，就算加班也给钱，济南大部分都是单休大小周，加班不给钱","createdAt":"2023-08-15T15:46:42"},{"id":"01963de6-53a1-7060-abf8-0fea82c860c2","parentId":null,"rootId":null,"fromId":3277,"content":"可以说说北京是啥情况吗，应该也有人想去外面看看","createdAt":"2023-08-16T21:53:05"},{"id":"01963de6-53e9-706b-a8e3-1657f64f12e3","parentId":null,"rootId":null,"fromId":3333,"content":"回来并不能歇歇，还是一样996，但是待遇要对半砍","createdAt":"2023-08-17T08:46:37"},{"id":"01963de6-5438-7187-b07b-4719dba0a77e","parentId":null,"rootId":null,"fromId":4029,"content":"济南老多公司都是那种工资都难发下来的，所以找工作的时候一定要好好查一下","createdAt":"2023-09-01T16:17:21"}]