[{"id":"01986317-b104-7184-94f0-43afc7b8164e","parentId":null,"rootId":null,"fromId":22444,"content":"坚持顶住，熬过去就有希望","createdAt":"2025-08-01T08:45:53"},{"id":"01986320-36df-705e-8844-2f283325eff7","parentId":null,"rootId":null,"fromId":2051,"content":"熬吧，没啥应对之策，如果迷茫了，可以自我提高一下，学学东西","createdAt":"2025-08-01T08:55:12"},{"id":"01986354-e760-7250-b22b-366f03eb8dd7","parentId":null,"rootId":null,"fromId":4016,"content":"学日语，英语，办护照","createdAt":"2025-08-01T09:52:45"},{"id":"01986367-b49f-73b9-b5f8-a6f669029aa3","parentId":null,"rootId":null,"fromId":6747,"content":"活阎王·","createdAt":"2025-08-01T10:13:17"},{"id":"0198644f-627d-7017-b6af-311dc01ca579","parentId":null,"rootId":null,"fromId":7566,"content":"去日本打工？","createdAt":"2025-08-01T14:26:20"}]