[{"id":"019879bc-3a67-70b5-9466-ff59f09ea766","parentId":null,"rootId":null,"fromId":1421,"content":"就是山海国旅，https://gshmd.vip/posts/01968c6d-ede3-70c1-8a60-b852ea14e218","createdAt":"2025-08-05T18:17:15"},{"id":"01988060-e2c7-7390-a87b-4ef34a99e396","parentId":null,"rootId":null,"fromId":22164,"content":"去年好像去过那天和一个小姑娘一起入职 她是上午走的我是下午走的","createdAt":"2025-08-07T01:14:49"},{"id":"0198825f-ee58-7232-b337-98f939aeee52","parentId":null,"rootId":null,"fromId":414,"content":"这么快提桶跑路吗，因为啥","createdAt":"2025-08-07T10:33:01"}]