[{"id":"0198984f-a641-7298-972e-c9ac8d153b19","parentId":null,"rootId":null,"fromId":6747,"content":"细说","createdAt":"2025-08-11T16:46:53"},{"id":"01989b68-86fc-733a-bc6b-1f24f12c8ca1","parentId":null,"rootId":null,"fromId":371,"content":"细说","createdAt":"2025-08-12T07:12:55"},{"id":"01989b6f-5624-70cc-a698-18d1689f3622","parentId":null,"rootId":null,"fromId":371,"content":"面过，给的很低","createdAt":"2025-08-12T07:20:21"},{"id":"01989d15-f214-72bf-bb45-85f1652e3421","parentId":null,"rootId":null,"fromId":6631,"content":"嘿嘿。待过北京的公司一段时间。当时福利挺好，就是工资低。","createdAt":"2025-08-12T15:01:57"},{"id":"019914f3-eaa5-72f7-9162-142ef57ee5be","parentId":null,"rootId":null,"fromId":26054,"content":"开发岗能不去就不去，就是基于一个已经做好的项目去售卖，然后根据客户那边的需求再去修改部分代码(毫无技术含量)，进去之后会拉你进N个项目群，全是以前历史遗留的问题，项目代码拉下来一堆报错，私库炸过一次，好多依赖都找不到","createdAt":"2025-09-04T21:39:13"}]