[{"id":"01981c57-2dec-737e-bb73-a2d0ef69205e","parentId":null,"rootId":null,"fromId":22913,"content":"最近没钱喝酒了","createdAt":"2025-07-18T15:02:12"},{"id":"01981c58-cb8f-71b7-8168-a28a32dc6426","parentId":null,"rootId":null,"fromId":23279,"content":"该喝还得喝啊，要不上班干什么","createdAt":"2025-07-18T15:03:58"},{"id":"01981c5a-2cc5-733d-ac6b-21cce6a5fc4e","parentId":null,"rootId":null,"fromId":6091,"content":"加盟费使劲砍呗，直接一万六千八","createdAt":"2025-07-18T15:05:28"},{"id":"01981c9c-fc52-71f3-af7b-0f11b44ffc24","parentId":null,"rootId":null,"fromId":1401,"content":"你自己想想从小到大多少砸到你头上的馅饼有多少","createdAt":"2025-07-18T16:18:27"},{"id":"01981cb4-6fee-706d-9787-28b1e64d2011","parentId":null,"rootId":null,"fromId":1421,"content":"富二代？","createdAt":"2025-07-18T16:44:03"},{"id":"01981cb5-25d4-72d5-8a0a-32688031baf1","parentId":null,"rootId":null,"fromId":460,"content":"哈哈哈哈哈哈哈哈哈哈哈哈哈","createdAt":"2025-07-18T16:44:50"},{"id":"01981cd0-0877-739e-89bd-fa9ec772831e","parentId":null,"rootId":null,"fromId":6747,"content":"利润70%为啥他不自己干？","createdAt":"2025-07-18T17:14:12"},{"id":"01982a89-9a08-7223-8d63-23daac7a32a5","parentId":null,"rootId":null,"fromId":24162,"content":"去掉房租、水电、人工、损耗等等再看看。当然啦，这些是你能有生意的情况下。。","createdAt":"2025-07-21T09:11:57"},{"id":"01982b0d-d306-7130-8855-8a046b859b04","parentId":null,"rootId":null,"fromId":25476,"content":"堵不堵，开不到一年就倒闭","createdAt":"2025-07-21T11:36:23"},{"id":"01982b83-65e6-72b8-957c-9eab6b00e3d7","parentId":null,"rootId":null,"fromId":460,"content":"兄弟 你这招不灵了 换个项目割韭菜吧","createdAt":"2025-07-21T13:44:48"},{"id":"01982bb8-d310-724e-aa1c-e74b5c976460","parentId":null,"rootId":null,"fromId":23279,"content":"不是我割韭菜啊，我这事准备当韭菜的节奏啊，不想当牛马了","createdAt":"2025-07-21T14:43:09"},{"id":"01982bf5-0859-706a-a115-08b1c2dc344b","parentId":null,"rootId":null,"fromId":5911,"content":"这样吧，盈利了给你70%，前期我一分不投入咋样？","createdAt":"2025-07-21T15:48:55"},{"id":"0198301a-74fb-73af-9ffd-facac08d53f4","parentId":null,"rootId":null,"fromId":22809,"content":"是韭菜你就干","createdAt":"2025-07-22T11:08:17"},{"id":"01986f9b-f4b2-703e-b2a3-53f72359ced6","parentId":null,"rootId":null,"fromId":270,"content":"这个利润怎么算出来的，招商经理有给你算过吗？利润达不到这个水平可以算违约退款吗？","createdAt":"2025-08-03T19:05:48"},{"id":"01991359-0f39-71c7-8742-092f17f49c0a","parentId":null,"rootId":null,"fromId":1538,"content":"为什么非要加盟,给别人加盟费送钱,你自己做一个品牌不行嘛","createdAt":"2025-09-04T14:10:27"}]